qmdx/__init__.py
qmdx/cli.py
qmdx/utils.py
qmdx/comm_x/__init__.py
qmdx/diff_x/__init__.py
qmdx/git_diff_x/__init__.py
qmdx-0.0.5.dist-info/LICENSE
qmdx-0.0.5.dist-info/METADATA
qmdx-0.0.5.dist-info/WHEEL
qmdx-0.0.5.dist-info/entry_points.txt
qmdx-0.0.5.dist-info/top_level.txt
qmdx-0.0.5.dist-info/RECORD
