Metadata-Version: 2.1
Name: qmdx
Version: 0.0.5
Summary: Pipe and diff files: execute shell pipelines against multiple inputs, diff/compare/join results.
Home-page: https://github.com/runsascoded/qmdx
Author: Ryan Williams
Author-email: ryan@runsascoded.com
License: MIT
License-File: LICENSE
Requires-Dist: click
Requires-Dist: utz>=0.13.0
